{
  "nLLP_original": 3788,
  "nLLP_original_weighted": 0.000198587381108,
  "nLLP_LLPdecay": 3788,
  "nLLP_LLPdecay_weighted": 0.000198587381108,
  "nLLP_InCavern": 92,
  "nLLP_InCavern_weighted": 4.823135972e-06,
  "nLLP_NotInATLAS": 38,
  "nLLP_NotInATLAS_weighted": 1.992164858e-06,
  "nLLP_Geometry": 7,
  "nLLP_Geometry_weighted": 3.66977737e-07,
  "nLLP_Tracker": 7,
  "nLLP_Tracker_weighted": 3.66977737e-07,
  "nLLP_MET": 5,
  "nLLP_MET_weighted": 2.62126955e-07,
  "nLLP_IsoJet": 4,
  "nLLP_IsoJet_weighted": 2.0970156400000001e-07,
  "nLLP_IsoCharged": 5,
  "nLLP_IsoCharged_weighted": 2.62126955e-07,
  "nLLP_IsoAll": 4,
  "nLLP_IsoAll_weighted": 2.0970156400000001e-07,
  "nLLP_partners": 0,
  "nLLP_partners_weighted": 0.0
}